{
  "minecraft:recipes/food/cake": {
    "criteria": {
      "has_egg": "2025-01-20 13:12:45 +0100"
    },
    "done": true
  },
  "minecraft:recipes/building_blocks/jungle_planks": {
    "criteria": {
      "has_logs": "2025-01-20 13:12:45 +0100"
    },
    "done": true
  },
  "minecraft:recipes/combat/bow": {
    "criteria": {
      "has_string": "2025-01-20 13:12:45 +0100"
    },
    "done": true
  },
  "minecraft:recipes/misc/charcoal": {
    "criteria": {
      "has_log": "2025-01-20 13:12:45 +0100"
    },
    "done": true
  },
  "minecraft:recipes/misc/lapis_lazuli": {
    "criteria": {
      "has_lapis_block": "2025-01-20 13:12:45 +0100"
    },
    "done": true
  },
  "minecraft:recipes/tools/fishing_rod": {
    "criteria": {
      "has_string": "2025-01-20 13:12:45 +0100"
    },
    "done": true
  },
  "minecraft:recipes/decorations/crafting_table": {
    "criteria": {
      "unlock_right_away": "2025-01-20 13:12:45 +0100"
    },
    "done": true
  },
  "minecraft:recipes/decorations/chest": {
    "criteria": {
      "has_lots_of_items": "2025-01-20 13:12:45 +0100"
    },
    "done": true
  },
  "minecraft:recipes/redstone/dispenser": {
    "criteria": {
      "has_bow": "2025-01-20 13:12:45 +0100"
    },
    "done": true
  },
  "minecraft:recipes/building_blocks/white_wool_from_string": {
    "criteria": {
      "has_string": "2025-01-20 13:12:45 +0100"
    },
    "done": true
  },
  "minecraft:recipes/misc/yellow_dye_from_dandelion": {
    "criteria": {
      "has_dandelion": "2025-01-20 13:12:45 +0100"
    },
    "done": true
  },
  "minecraft:recipes/redstone/tripwire_hook": {
    "criteria": {
      "has_string": "2025-01-20 13:12:45 +0100"
    },
    "done": true
  },
  "minecraft:recipes/misc/bone_meal": {
    "criteria": {
      "has_bone": "2025-01-20 13:12:45 +0100"
    },
    "done": true
  },
  "minecraft:recipes/combat/crossbow": {
    "criteria": {
      "has_string": "2025-01-20 13:12:45 +0100"
    },
    "done": true
  },
  "minecraft:recipes/decorations/candle": {
    "criteria": {
      "has_string": "2025-01-20 13:12:45 +0100"
    },
    "done": true
  },
  "minecraft:recipes/misc/firework_rocket_simple": {
    "criteria": {
      "has_gunpowder": "2025-01-20 13:12:45 +0100"
    },
    "done": true
  },
  "minecraft:recipes/redstone/tnt": {
    "criteria": {
      "has_gunpowder": "2025-01-20 13:12:45 +0100"
    },
    "done": true
  },
  "minecraft:recipes/decorations/jungle_hanging_sign": {
    "criteria": {
      "has_stripped_logs": "2025-01-20 13:12:45 +0100"
    },
    "done": true
  },
  "minecraft:recipes/decorations/loom": {
    "criteria": {
      "has_string": "2025-01-20 13:12:45 +0100"
    },
    "done": true
  },
  "minecraft:recipes/building_blocks/stripped_jungle_wood": {
    "criteria": {
      "has_log": "2025-01-20 13:12:45 +0100"
    },
    "done": true
  },
  "minecraft:adventure/adventuring_time": {
    "criteria": {
      "minecraft:birch_forest": "2025-01-20 13:12:48 +0100",
      "minecraft:meadow": "2025-01-20 13:12:46 +0100"
    },
    "done": false
  },
  "minecraft:recipes/combat/iron_sword": {
    "criteria": {
      "has_iron_ingot": "2025-01-30 20:20:59 +0100"
    },
    "done": true
  },
  "minecraft:recipes/tools/iron_pickaxe": {
    "criteria": {
      "has_iron_ingot": "2025-01-30 20:20:59 +0100"
    },
    "done": true
  },
  "minecraft:recipes/combat/leather_helmet": {
    "criteria": {
      "has_leather": "2025-01-30 20:20:59 +0100"
    },
    "done": true
  },
  "minecraft:recipes/combat/iron_leggings": {
    "criteria": {
      "has_iron_ingot": "2025-01-30 20:20:59 +0100"
    },
    "done": true
  },
  "minecraft:recipes/combat/shield": {
    "criteria": {
      "has_iron_ingot": "2025-01-30 20:20:59 +0100"
    },
    "done": true
  },
  "minecraft:recipes/redstone/hopper": {
    "criteria": {
      "has_iron_ingot": "2025-01-30 20:20:59 +0100"
    },
    "done": true
  },
  "minecraft:recipes/combat/leather_leggings": {
    "criteria": {
      "has_leather": "2025-01-30 20:20:59 +0100"
    },
    "done": true
  },
  "minecraft:recipes/decorations/iron_bars": {
    "criteria": {
      "has_iron_ingot": "2025-01-30 20:20:59 +0100"
    },
    "done": true
  },
  "minecraft:recipes/combat/iron_boots": {
    "criteria": {
      "has_iron_ingot": "2025-01-30 20:20:59 +0100"
    },
    "done": true
  },
  "minecraft:recipes/combat/iron_chestplate": {
    "criteria": {
      "has_iron_ingot": "2025-01-30 20:20:59 +0100"
    },
    "done": true
  },
  "minecraft:recipes/brewing/magma_cream": {
    "criteria": {
      "has_blaze_powder": "2025-01-30 20:20:59 +0100"
    },
    "done": true
  },
  "minecraft:recipes/decorations/lantern": {
    "criteria": {
      "has_iron_ingot": "2025-01-30 20:20:59 +0100"
    },
    "done": true
  },
  "minecraft:recipes/building_blocks/polished_blackstone_bricks_from_polished_blackstone_stonecutting": {
    "criteria": {
      "has_polished_blackstone": "2025-01-30 20:20:59 +0100"
    },
    "done": true
  },
  "minecraft:recipes/misc/iron_nugget": {
    "criteria": {
      "has_iron_ingot": "2025-01-30 20:20:59 +0100"
    },
    "done": true
  },
  "minecraft:recipes/misc/bucket": {
    "criteria": {
      "has_iron_ingot": "2025-01-30 20:20:59 +0100"
    },
    "done": true
  },
  "minecraft:recipes/combat/iron_helmet": {
    "criteria": {
      "has_iron_ingot": "2025-01-30 20:20:59 +0100"
    },
    "done": true
  },
  "minecraft:recipes/transportation/minecart": {
    "criteria": {
      "has_iron_ingot": "2025-01-30 20:20:59 +0100"
    },
    "done": true
  },
  "minecraft:recipes/tools/iron_hoe": {
    "criteria": {
      "has_iron_ingot": "2025-01-30 20:20:59 +0100"
    },
    "done": true
  },
  "minecraft:recipes/tools/iron_shovel": {
    "criteria": {
      "has_iron_ingot": "2025-01-30 20:20:59 +0100"
    },
    "done": true
  },
  "minecraft:recipes/building_blocks/chiseled_polished_blackstone_from_polished_blackstone_stonecutting": {
    "criteria": {
      "has_polished_blackstone": "2025-01-30 20:20:59 +0100"
    },
    "done": true
  },
  "minecraft:recipes/decorations/item_frame": {
    "criteria": {
      "has_leather": "2025-01-30 20:20:59 +0100"
    },
    "done": true
  },
  "minecraft:recipes/building_blocks/polished_blackstone_stairs_from_polished_blackstone_stonecutting": {
    "criteria": {
      "has_polished_blackstone": "2025-01-30 20:20:59 +0100"
    },
    "done": true
  },
  "minecraft:recipes/combat/leather_chestplate": {
    "criteria": {
      "has_leather": "2025-01-30 20:20:59 +0100"
    },
    "done": true
  },
  "minecraft:recipes/building_blocks/polished_blackstone_slab_from_polished_blackstone_stonecutting": {
    "criteria": {
      "has_polished_blackstone": "2025-01-30 20:20:59 +0100"
    },
    "done": true
  },
  "minecraft:recipes/building_blocks/polished_blackstone_stairs": {
    "criteria": {
      "has_polished_blackstone": "2025-01-30 20:20:59 +0100"
    },
    "done": true
  },
  "minecraft:story/smelt_iron": {
    "criteria": {
      "iron": "2025-01-30 20:20:59 +0100"
    },
    "done": true
  },
  "minecraft:recipes/building_blocks/polished_blackstone_brick_stairs_from_polished_blackstone_stonecutting": {
    "criteria": {
      "has_polished_blackstone": "2025-01-30 20:20:59 +0100"
    },
    "done": true
  },
  "minecraft:recipes/tools/shears": {
    "criteria": {
      "has_iron_ingot": "2025-01-30 20:20:59 +0100"
    },
    "done": true
  },
  "minecraft:recipes/redstone/polished_blackstone_button": {
    "criteria": {
      "has_polished_blackstone": "2025-01-30 20:20:59 +0100"
    },
    "done": true
  },
  "minecraft:recipes/decorations/polished_blackstone_wall_from_polished_blackstone_stonecutting": {
    "criteria": {
      "has_polished_blackstone": "2025-01-30 20:20:59 +0100"
    },
    "done": true
  },
  "minecraft:recipes/redstone/iron_trapdoor": {
    "criteria": {
      "has_iron_ingot": "2025-01-30 20:20:59 +0100"
    },
    "done": true
  },
  "minecraft:recipes/misc/ender_eye": {
    "criteria": {
      "has_blaze_powder": "2025-01-30 20:20:59 +0100"
    },
    "done": true
  },
  "minecraft:recipes/decorations/chain": {
    "criteria": {
      "has_iron_ingot": "2025-01-30 20:20:59 +0100"
    },
    "done": true
  },
  "minecraft:recipes/redstone/polished_blackstone_pressure_plate": {
    "criteria": {
      "has_polished_blackstone": "2025-01-30 20:20:59 +0100"
    },
    "done": true
  },
  "minecraft:recipes/building_blocks/polished_blackstone_brick_slab_from_polished_blackstone_stonecutting": {
    "criteria": {
      "has_polished_blackstone": "2025-01-30 20:20:59 +0100"
    },
    "done": true
  },
  "minecraft:recipes/building_blocks/iron_block": {
    "criteria": {
      "has_iron_ingot": "2025-01-30 20:20:59 +0100"
    },
    "done": true
  },
  "minecraft:recipes/tools/iron_axe": {
    "criteria": {
      "has_iron_ingot": "2025-01-30 20:20:59 +0100"
    },
    "done": true
  },
  "minecraft:recipes/decorations/smithing_table": {
    "criteria": {
      "has_iron_ingot": "2025-01-30 20:20:59 +0100"
    },
    "done": true
  },
  "minecraft:recipes/building_blocks/polished_blackstone_slab": {
    "criteria": {
      "has_polished_blackstone": "2025-01-30 20:20:59 +0100"
    },
    "done": true
  },
  "minecraft:recipes/combat/leather_boots": {
    "criteria": {
      "has_leather": "2025-01-30 20:20:59 +0100"
    },
    "done": true
  },
  "minecraft:recipes/misc/fire_charge": {
    "criteria": {
      "has_blaze_powder": "2025-01-30 20:20:59 +0100"
    },
    "done": true
  },
  "minecraft:recipes/misc/leather_horse_armor": {
    "criteria": {
      "has_leather": "2025-01-30 20:20:59 +0100"
    },
    "done": true
  },
  "minecraft:recipes/building_blocks/polished_blackstone_bricks": {
    "criteria": {
      "has_polished_blackstone": "2025-01-30 20:20:59 +0100"
    },
    "done": true
  },
  "minecraft:recipes/redstone/iron_door": {
    "criteria": {
      "has_iron_ingot": "2025-01-30 20:20:59 +0100"
    },
    "done": true
  },
  "minecraft:recipes/decorations/polished_blackstone_wall": {
    "criteria": {
      "has_polished_blackstone": "2025-01-30 20:20:59 +0100"
    },
    "done": true
  },
  "minecraft:recipes/redstone/heavy_weighted_pressure_plate": {
    "criteria": {
      "has_iron_ingot": "2025-01-30 20:20:59 +0100"
    },
    "done": true
  },
  "minecraft:recipes/decorations/polished_blackstone_brick_wall_from_polished_blackstone_stonecutting": {
    "criteria": {
      "has_polished_blackstone": "2025-01-30 20:20:59 +0100"
    },
    "done": true
  },
  "DataVersion": 3465
}